{
  "schema": "autoskill.document.parent_children_manifest.v1",
  "generated_at": "2026-04-08T11:05:12+00:00",
  "domain_root_name": "心理咨询",
  "family_name": "认知行为疗法",
  "profile_id": "psychology::认知行为疗法",
  "taxonomy_axis": "疗法",
  "parent_skill_id": "24243fe5-e8a3-5eae-a4ca-1251adbfc97e",
  "parent_name": "合理情绪疗法四阶段咨询框架",
  "children": [
    {
      "skill_id": "cb7fdbac-e222-5214-ad0a-2ef99b0d632c",
      "name": "ABC理论导入与初步问题分析",
      "description": "首次咨询中系统介绍ABC模型并结合心理测验结果进行初步问题归因，旨在建立共同理解框架并启动认知觉察。",
      "child_type": "认知行为干预",
      "asset_node_id": "session_framework",
      "asset_path": "family_root/treatment_framework/session_framework",
      "asset_level": 2,
      "parent_skill_id": "24243fe5-e8a3-5eae-a4ca-1251adbfc97e",
      "level_label": "二级技能",
      "taxonomy_class": "认知行为疗法",
      "applicable_when": "首次咨询中系统介绍ABC模型并结合心理测验结果进行初步问题归因，旨在建立共同理解框架并启动认知觉察。",
      "selector_terms": [
        "首次咨询且个案对情绪困扰成因缺乏认知解释框架",
        "已获取SAS/SDS等标准化测验数据",
        "CBT",
        "合理情绪疗法",
        "初次会谈",
        "心理教育",
        "认知概念化",
        "求助者用‘都是因为……’句式归因情绪（如‘都是因为他甩了我，我才这么痛苦’）",
        "求助者将情绪反应视为事件必然结果，未觉察中间信念环节",
        "ABC理论导入与初步问题分析",
        "首次咨询中系统介绍ABC模型并结合心理测验结果进行初步问题归因，旨在建立共同理解框架并启动认知觉察。"
      ],
      "relative_path": "心理咨询/Family技能/认知行为疗法/二级技能/ABC理论导入与初步问题分析/SKILL.md"
    },
    {
      "skill_id": "774a8e5b-f80f-55cc-a6a7-465d41fe278e",
      "name": "CBT核心信念识别与协同重构",
      "description": "在咨询初期、信任关系已初步建立的前提下，运用CBT认知概念化框架识别求助者不合理核心信念，并通过苏格拉底式提问、证据检验与协作生成等方式，引导其发展更具现实性、适应性与弹性的替代信念。",
      "child_type": "认知重构",
      "asset_node_id": "session_framework",
      "asset_path": "family_root/treatment_framework/session_framework",
      "asset_level": 2,
      "parent_skill_id": "24243fe5-e8a3-5eae-a4ca-1251adbfc97e",
      "level_label": "二级技能",
      "taxonomy_class": "认知行为疗法",
      "applicable_when": "在咨询初期、信任关系已初步建立的前提下，运用CBT认知概念化框架识别求助者不合理核心信念，并通过苏格拉底式提问、证据检验与协作生成等方式，引导其发展更具现实性、适应性与弹性的替代信念。",
      "selector_terms": [
        "求助者表现出情绪困扰但尚未明确自动思维链",
        "已有初步咨访关系基础",
        "可配合完成结构化自我报告",
        "CBT",
        "核心信念",
        "认知概念化",
        "信念重构",
        "结构化干预",
        "求助者能描述具体人际/学业事件并关联情绪反应",
        "愿意尝试回忆过去类似经历",
        "对‘想法是否绝对真实’类提问表现出思考意愿",
        "CBT核心信念识别与协同重构",
        "在咨询初期、信任关系已初步建立的前提下，运用CBT认知概念化框架识别求助者不合理核心信念，并通过苏格拉底式提问、证据检验与协作生成等方式，引导其发展更具现实性、适应性与弹性的替代信念。"
      ],
      "relative_path": "心理咨询/Family技能/认知行为疗法/二级技能/CBT核心信念识别与协同重构/SKILL.md"
    },
    {
      "skill_id": "dd6ac27d-9b04-5491-8bc1-3dff9fdeefd7",
      "name": "情绪管理表归因探询",
      "description": "基于来访者填写的情绪管理表，聚焦‘情绪低落/消极言行超出目标’的偏差条目，采用事件—认知—情绪链回溯法，定位当日触发事件与中间非理性认知节点。",
      "child_type": "行为—认知联结评估",
      "asset_node_id": "session_framework",
      "asset_path": "family_root/treatment_framework/session_framework",
      "asset_level": 2,
      "parent_skill_id": "24243fe5-e8a3-5eae-a4ca-1251adbfc97e",
      "level_label": "二级技能",
      "taxonomy_class": "认知行为疗法",
      "applicable_when": "基于来访者填写的情绪管理表，聚焦‘情绪低落/消极言行超出目标’的偏差条目，采用事件—认知—情绪链回溯法，定位当日触发事件与中间非理性认知节点。",
      "selector_terms": [
        "来访者规律完成情绪记录作业",
        "存在可比对的目标值与实际值偏差",
        "偏差发生在非危机情境下",
        "CBT",
        "情绪管理",
        "自动思维识别",
        "作业反馈",
        "归因探询",
        "来访者主动提及某次情绪波动与预期不符",
        "情绪管理表中出现≥1处清晰标记的‘超标’或‘未达标’条目",
        "来访者能回忆当日基本情境但尚未连接认知环节",
        "情绪管理表归因探询",
        "基于来访者填写的情绪管理表，聚焦‘情绪低落/消极言行超出目标’的偏差条目，采用事件—认知—情绪链回溯法，定位当日触发事件与中间非理性认知节点。"
      ],
      "relative_path": "心理咨询/Family技能/认知行为疗法/二级技能/情绪管理表归因探询/SKILL.md"
    }
  ]
}